BalancedRoutePlanner/BalancedRoutePlanner.py
BalancedRoutePlanner/__init__.py
tests/__init__.py
tests/test.py
BalancedRoutePlanner-1.0.0.dist-info/LICENSE.txt
BalancedRoutePlanner-1.0.0.dist-info/METADATA
BalancedRoutePlanner-1.0.0.dist-info/WHEEL
BalancedRoutePlanner-1.0.0.dist-info/top_level.txt
BalancedRoutePlanner-1.0.0.dist-info/RECORD
