Metadata-Version: 2.1
Name: BalancedRoutePlanner
Version: 1.0.0
Summary: A package for balanced clustering and route planning
Home-page: https://github.com/SmartCitiesTransportationHub/BalancedRoutePlanner
Author: ['Shuotong Su']
Author-email: ['906131501@qq.com']
License: MIT
Classifier: Programming Language :: Python :: 3
Classifier: License :: OSI Approved :: MIT License
Classifier: Operating System :: OS Independent
Requires-Python: >=3.6
License-File: LICENSE.txt
Requires-Dist: numpy
Requires-Dist: matplotlib
Requires-Dist: scikit-learn
